fastapi_mock/__init__.py
fastapi_mock/example_provider.py
fastapi_mock/logging_.py
fastapi_mock/mock.py
fastapi_mock-0.3.4.dist-info/LICENSE
fastapi_mock-0.3.4.dist-info/METADATA
fastapi_mock-0.3.4.dist-info/WHEEL
fastapi_mock-0.3.4.dist-info/RECORD
