Metadata-Version: 2.1
Name: fastapi-mock
Version: 0.3.4
Summary: A utility for FastAPI that allows you to create mock endpoints quickly and easily.
Author: Ruslan Belckov
Author-email: ruslan.belckov@yandex.ru
Requires-Python: >=3.10,<4.0
Classifier: License :: OSI Approved :: MIT License
Classifier: Operating System :: OS Independent
Classifier: Programming Language :: Python :: 3
Classifier: Programming Language :: Python :: 3.10
Classifier: Programming Language :: Python :: 3.11
Classifier: Programming Language :: Python :: 3.12
Requires-Dist: fastapi (>=0.104)
Requires-Dist: pydantic (>=2,<3)
Project-URL: Bug Tracker, https://github.com/dantetemplar/fastapi-mock/issues
Project-URL: Homepage, https://github.com/dantetemplar/fastapi-mock
